queryable/__init__.py
queryable/queryable.py
queryable-0.1.dev0.dist-info/DESCRIPTION.rst
queryable-0.1.dev0.dist-info/METADATA
queryable-0.1.dev0.dist-info/RECORD
queryable-0.1.dev0.dist-info/WHEEL
queryable-0.1.dev0.dist-info/metadata.json
queryable-0.1.dev0.dist-info/top_level.txt
